{
  "groups": [
    {
      "name": "uri.broker",
      "type": "br.com.cvc.domain.utils.UriProperties",
      "sourceType": "br.com.cvc.domain.utils.UriProperties"
    }
  ],
  "properties": [
    {
      "name": "uri.broker.host-cvc-backend-hotel",
      "type": "java.lang.String",
      "sourceType": "br.com.cvc.domain.utils.UriProperties"
    },
    {
      "name": "uri.broker.hotels",
      "type": "java.lang.String",
      "sourceType": "br.com.cvc.domain.utils.UriProperties"
    },
    {
      "name": "uri.broker.hotels-avail",
      "type": "java.lang.String",
      "sourceType": "br.com.cvc.domain.utils.UriProperties"
    },
    {
      "name": "uri.broker.https",
      "type": "java.lang.String",
      "sourceType": "br.com.cvc.domain.utils.UriProperties"
    }
  ],
  "hints": []
}